django_ai_core/__init__.py
django_ai_core/apps.py
django_ai_core/contrib/agents/__init__.py
django_ai_core/contrib/agents/base.py
django_ai_core/contrib/agents/permissions.py
django_ai_core/contrib/agents/urls.py
django_ai_core/contrib/agents/views.py
django_ai_core/contrib/index/__init__.py
django_ai_core/contrib/index/apps.py
django_ai_core/contrib/index/base.py
django_ai_core/contrib/index/chunking.py
django_ai_core/contrib/index/embedding.py
django_ai_core/contrib/index/embedding_cache.py
django_ai_core/contrib/index/management/__init__.py
django_ai_core/contrib/index/management/commands/__init__.py
django_ai_core/contrib/index/management/commands/rebuild_indexes.py
django_ai_core/contrib/index/migrations/0001_initial.py
django_ai_core/contrib/index/migrations/__init__.py
django_ai_core/contrib/index/models.py
django_ai_core/contrib/index/query.py
django_ai_core/contrib/index/schema.py
django_ai_core/contrib/index/signals.py
django_ai_core/contrib/index/source.py
django_ai_core/contrib/index/storage/__init__.py
django_ai_core/contrib/index/storage/base.py
django_ai_core/contrib/index/storage/inmemory.py
django_ai_core/contrib/index/storage/llamaindex.py
django_ai_core/contrib/index/storage/pgvector/__init__.py
django_ai_core/contrib/index/storage/pgvector/apps.py
django_ai_core/contrib/index/storage/pgvector/migrations/0001_initial.py
django_ai_core/contrib/index/storage/pgvector/migrations/__init__.py
django_ai_core/contrib/index/storage/pgvector/models.py
django_ai_core/contrib/index/storage/pgvector/provider.py
django_ai_core/contrib/index/storage/qdrant.py
django_ai_core/contrib/index/storage/s3vectors.py
django_ai_core/llm/__init__.py
django_ai_core/llm/base.py
django_ai_core/llm/prompt.py
django_ai_core-0.1.5.dist-info/licenses/LICENSE
django_ai_core-0.1.5.dist-info/WHEEL
django_ai_core-0.1.5.dist-info/METADATA
django_ai_core-0.1.5.dist-info/RECORD
